holmium/__init__.py
holmium/core/__init__.py
holmium/core/_version.py
holmium/core/conditions.py
holmium/core/config.py
holmium/core/enhancers.py
holmium/core/env.py
holmium/core/facets.py
holmium/core/logger.py
holmium/core/pageobject.py
holmium/core/testcase.py
holmium/core/version.py
holmium.core-1.1.0.dist-info/LICENSE.txt
holmium.core-1.1.0.dist-info/METADATA
holmium.core-1.1.0.dist-info/WHEEL
holmium.core-1.1.0.dist-info/top_level.txt
holmium.core-1.1.0.dist-info/RECORD
